dude.py
dude-0.1.3.dist-info/METADATA
dude-0.1.3.dist-info/WHEEL
dude-0.1.3.dist-info/entry_points.txt
dude-0.1.3.dist-info/RECORD
