Metadata-Version: 2.1
Name: dude
Version: 0.1.3
Summary: tool similar to du but a little fancier i guess
Home-page: https://github.com/hannahherbig/dude
License: MIT
Author: Hannah Herbig
Author-email: nothannahherbig@gmail.com
Requires-Python: >=3.7,<4.0
Classifier: Development Status :: 1 - Planning
Classifier: Intended Audience :: Developers
Classifier: License :: OSI Approved :: MIT License
Classifier: Programming Language :: Python
Classifier: Programming Language :: Python :: 3
Classifier: Programming Language :: Python :: 3.7
Classifier: Programming Language :: Python :: 3.8
Classifier: Programming Language :: Python :: 3.9
Classifier: Programming Language :: Python :: 3.10
Classifier: Programming Language :: Python :: 3.11
Requires-Dist: humanize (>=3.1,<5.0)
Requires-Dist: tabulate (>=0.8.7,<0.10.0)
Project-URL: Repository, https://github.com/hannahherbig/dude
